chainpoint/__init__.py
chainpoint/chainpoint.py
chainpoint/tests/__init__.py
chainpoint/tests/chainpoint_test.py
chainpointupdate-0.0.2.dist-info/METADATA
chainpointupdate-0.0.2.dist-info/WHEEL
chainpointupdate-0.0.2.dist-info/top_level.txt
chainpointupdate-0.0.2.dist-info/RECORD
