Metadata-Version: 2.1
Name: chainpointupdate
Version: 0.0.2
Summary: Chainpoint proof of existance library
Home-page: https://github.com/lontivero/pychainpoint
Author: Lucas Ontivero
Author-email: lucasontivero@gmail.com
License: MIT
Keywords: chainpoint,proof of existance,blockchain,merkle tree,bitcoin
Platform: UNKNOWN
Classifier: Intended Audience :: Developers
Classifier: Intended Audience :: Science/Research
Classifier: License :: OSI Approved :: MIT License
Classifier: Programming Language :: Python :: 2.7
Requires-Dist: merkletools (>=1.0.2)
